stocklib/__init__.py
stocklib/client.py
stocklib/analysis/__init__.py
stocklib/analysis/growth.py
stocklib/analysis/ratios.py
stocklib/analysis/risk.py
stocklib/analysis/valuation.py
stocklib/cache/__init__.py
stocklib/cache/interface.py
stocklib/cache/redis.py
stocklib/core/__init__.py
stocklib/core/context.py
stocklib/core/orchestrator.py
stocklib/core/pipeline.py
stocklib/exceptions/__init__.py
stocklib/exceptions/data.py
stocklib/exceptions/provider.py
stocklib/exceptions/rate_limit.py
stocklib/models/__init__.py
stocklib/models/company.py
stocklib/models/financials.py
stocklib/models/fundamentals.py
stocklib/models/growth.py
stocklib/models/market.py
stocklib/models/metadata.py
stocklib/models/ratios.py
stocklib/models/risk.py
stocklib/providers/__init__.py
stocklib/providers/alpha_vantage.py
stocklib/providers/base.py
stocklib/providers/fmp.py
stocklib/rate_limit/__init__.py
stocklib/rate_limit/interface.py
stocklib/rate_limit/redis_rate_limitter.py
stocklib/rate_limit/token_bucket.py
stocklib/utils/__init__.py
stocklib/utils/config.py
stocklib/utils/retry.py
stocklib_strawhat-0.2.0.dist-info/METADATA
stocklib_strawhat-0.2.0.dist-info/WHEEL
stocklib_strawhat-0.2.0.dist-info/top_level.txt
stocklib_strawhat-0.2.0.dist-info/RECORD
