Metadata-Version: 2.4
Name: stocklib-strawhat
Version: 0.2.0
Summary: Stock fundamentals analysis library
Author-email: Sarang <technicalstrawhat@gmail.com>
License: MIT
Project-URL: Repository, https://github.com/imsarang/stock-lib
Classifier: Programming Language :: Python :: 3
Classifier: License :: OSI Approved :: MIT License
Classifier: Operating System :: OS Independent
Requires-Python: >=3.8
Requires-Dist: aiohttp>=3.13.0
Requires-Dist: pydantic>=2.0.0
Requires-Dist: redis>=5.0.0
Requires-Dist: python-dotenv>=1.0.0
